part2/alu.v
module alu  (
    // Data input.
    input  [7:0] X,
    input  [7:0] Y,

    // alu controller
    input op,

    // Data output.
    output [8:0] Result   

);

reg [8:0] temporary;

always @( * ) // while(True) loop
    begin: alu_code
    if (op == 0) begin
        temporary = X + Y;
    end else begin
        temporary = X - Y;
    end
end 

assign Result = temporary;

endmodule

part2/alu_wave.vcd
$version Generated by VerilatedVcd $end
$date Thu Feb 17 20:02:44 2022 $end
$timescale 1ps $end

 $scope module TOP $end
  $var wire  9 & Result [8:0] $end
  $var wire  8 # X [7:0] $end
  $var wire  8 $ Y [7:0] $end
  $var wire  1 % op $end
  $scope module alu $end
   $var wire  9 & Result [8:0] $end
   $var wire  8 # X [7:0] $end
   $var wire  8 $ Y [7:0] $end
   $var wire  1 % op $end
   $var wire  9 ' temporary [8:0] $end
  $upscope $end
 $upscope $end
$enddefinitions $end


#0
b00001110 #
b00100111 $
1%
b111100111 &
b111100111 '
#1
b01000011 #
b00111100 $
b000000111 &
b000000111 '
#2
b00110111 #
b01100010 $
0%
b010011001 &
b010011001 '
#3
b00110101 #
b01001011 $
1%
b111101010 &
b111101010 '
#4
b01000010 #
b00100001 $
0%
b001100011 &
b001100011 '
#5
b01000111 #
b00111010 $
1%
b000001101 &
b000001101 '
#6
b01000000 #
b00000001 $
0%
b001000001 &
b001000001 '
#7
b00011000 #
b00011100 $
1%
b111111100 &
b111111100 '
#8
b00110111 #
b00111100 $
0%
b001110011 &
b001110011 '
#9
b00100000 #
b00100100 $
b001000100 &
b001000100 '
#10
b00111110 #
b00110010 $
1%
b000001100 &
b000001100 '
#11
b01000101 #
b01000110 $
b111111111 &
b111111111 '
#12
b00001010 #
b00011001 $
b111110001 &
b111110001 '
#13
b00100010 #
b00011110 $
b000000100 &
b000000100 '
#14
b01001100 #
b00110000 $
0%
b001111100 &
b001111100 '
#15
b01100000 #
b00010011 $
b001110011 &
b001110011 '
#16
b00000011 #
b00100100 $
b000100111 &
b000100111 '
#17
b00100010 #
b00111100 $
b001011110 &
b001011110 '
#18
b01001011 #
b01000011 $
b010001110 &
b010001110 '
#19
b00011111 #
b00110011 $
1%
b111101100 &
b111101100 '
#20
b01000011 #
b00001110 $
b000110101 &
b000110101 '
#21
b01011110 #
b00100011 $
b000111011 &
b000111011 '
#22
b01010010 #
b00101110 $
0%
b010000000 &
b010000000 '
#23
b01000011 #
b00100000 $
1%
b000100011 &
b000100011 '
#24
b00011100 #
b00111100 $
b111100000 &
b111100000 '
#25
b01001011 #
b00001000 $
b001000011 &
b001000011 '
#26
b01001111 #
b00001100 $
#27
b00100001 #
b01100010 $
b110111111 &
b110111111 '
#28
b00010100 #
b00011001 $
0%
b000101101 &
b000101101 '
#29
b01000010 #
b00001000 $
1%
b000111010 &
b000111010 '
