part1/Ten2OneMux.v
module Ten2OneMux(
    // Inputs    
    input wire [7:0] D0,
    input wire [7:0] D1,
    input wire [7:0] D2,
    input wire [7:0] D3,
    input wire [7:0] D4,
    input wire [7:0] D5,
    input wire [7:0] D6,
    input wire [7:0] D7,
    input wire [7:0] D8,
    input wire [7:0] D9,
    input wire [3:0] select,
    
    // Output
    output reg [7:0] Output       
    ); 


// Input selection according to the selector value
always@( * ) // while(True) loop
    begin
    case(select)
    4'b0000: Output=D0;
    4'b0001: Output=D1;
    4'b0010: Output=D2;
    4'b0011: Output=D3;
    4'b0100: Output=D4;
    4'b0101: Output=D5;
    4'b0110: Output=D6;
    4'b0111: Output=D7;
    4'b1000: Output=D8;
    4'b1001: Output=D9;
    default: Output=8'b00000000;
    endcase    
end
endmodule

part1/Ten2OneMux_wave.vcd
$version Generated by VerilatedVcd $end
$date Thu Feb 17 20:11:08 2022 $end
$timescale 1ps $end

 $scope module TOP $end
  $var wire  8 # D0 [7:0] $end
  $var wire  8 $ D1 [7:0] $end
  $var wire  8 % D2 [7:0] $end
  $var wire  8 & D3 [7:0] $end
  $var wire  8 ' D4 [7:0] $end
  $var wire  8 ( D5 [7:0] $end
  $var wire  8 ) D6 [7:0] $end
  $var wire  8 * D7 [7:0] $end
  $var wire  8 + D8 [7:0] $end
  $var wire  8 , D9 [7:0] $end
  $var wire  8 . Output [7:0] $end
  $var wire  4 - select [3:0] $end
  $scope module Ten2OneMux $end
   $var wire  8 # D0 [7:0] $end
   $var wire  8 $ D1 [7:0] $end
   $var wire  8 % D2 [7:0] $end
   $var wire  8 & D3 [7:0] $end
   $var wire  8 ' D4 [7:0] $end
   $var wire  8 ( D5 [7:0] $end
   $var wire  8 ) D6 [7:0] $end
   $var wire  8 * D7 [7:0] $end
   $var wire  8 + D8 [7:0] $end
   $var wire  8 , D9 [7:0] $end
   $var wire  8 . Output [7:0] $end
   $var wire  4 - select [3:0] $end
  $upscope $end
 $upscope $end
$enddefinitions $end


#0
b00001110 #
b10000011 $
b00001011 %
b01110011 &
b11101100 '
b11110101 (
b01001011 )
b01001010 *
b01110100 +
b00110101 ,
b0101 -
b11110101 .
#1
b11110001 #
b00000110 $
b01000001 %
b11001000 &
b01101011 '
b10101010 (
b11011111 )
b00001100 *
b00111101 +
b11100110 ,
b0100 -
b01101011 .
#2
b01001000 #
b10100001 $
b11011011 %
b11010100 &
b01101000 '
b01111000 (
b11011100 )
b01011000 *
b01001110 +
b11101010 ,
b0101 -
b01111000 .
#3
b01011001 #
b01011110 $
b11000111 %
b01001110 &
b10101001 '
b00010001 (
b11000010 )
b11011110 *
b11111001 +
b10110100 ,
b1000 -
b11111001 .
#4
b00111010 #
b01111100 $
b01001111 %
b11100100 &
b01011011 '
b01011100 (
b00100010 )
b01000010 *
b10101000 +
b01101010 ,
b0101 -
b01011100 .
#5
b10000011 #
b00111110 $
b01001011 %
b11111011 &
b00011011 '
b10100011 (
b01001010 )
b00000101 *
b01111110 +
b10100011 ,
b0111 -
b00000101 .
#6
b01000110 #
b11110010 $
b00001100 %
b01010111 &
b10110100 '
b11101011 (
b01010000 )
b01101000 *
b11001111 +
b10001011 ,
b1000 -
b11001111 .
#7
b00011111 #
b01101111 $
b01000000 %
b01111011 &
b10010001 '
b10000010 (
b00100011 )
b11111100 *
b01100101 +
b10100110 ,
b0110 -
b00100011 .
#8
b10110000 #
b10100001 $
b01010101 %
b01010011 &
b11101011 '
b01011011 (
b11010001 )
b10001111 *
b10111110 +
b00010111 ,
b0001 -
b10100001 .
#9
b11001011 #
b01101111 $
b00110101 %
b10110110 &
b10111111 '
b10011110 (
b10000101 )
b01001010 *
b10000010 +
b10100100 ,
b1000 -
b10000010 .
#10
b11000010 #
b00011111 $
b01001011 %
b01000100 &
b01000010 '
b01000111 (
b10101001 )
b11101000 *
b01011001 ,
b0000 -
b11000010 .
#11
b11010111 #
b10101100 $
b01110101 %
b00110010 &
b01111110 '
b00000100 (
b11110001 )
b10010101 *
b10000101 +
b10111100 ,
b11010111 .
#12
b10111011 #
b01110010 $
b11000100 %
b01011001 &
b11110111 '
b00001110 (
b11011011 )
b10011100 *
b11001000 +
b10011110 ,
b1001 -
b10011110 .
#13
b00010100 #
b11100010 $
b11111110 %
b01011011 &
b10001100 '
b11100110 (
b11011101 )
b11100101 *
b01110000 +
b10110101 ,
b1000 -
b01110000 .
#14
b11100110 #
b11100111 $
b00010000 %
b11101010 &
b11011000 '
b10100101 (
b01110000 )
b10010100 *
b10101010 +
b00101011 ,
b0110 -
#15
b01101110 #
b10000100 $
b11111110 %
b01111100 &
b01011111 '
b10011010 (
b01000101 )
b11111101 *
b01010101 +
b01011001 ,
b01000101 .
#16
b01010011 #
b10110100 $
b01101100 %
b00111010 &
b10010010 '
b01010001 (
b10101010 )
b01000111 *
b11100011 +
b10010000 ,
b1000 -
b11100011 .
#17
b11110011 #
b01111011 $
b00000111 %
b10011001 &
b11101011 '
b10011011 (
b01000011 )
b00010110 *
b10100010 +
b10110001 ,
b0010 -
b00000111 .
#18
b10100000 #
b00101101 $
b11111001 %
b00111010 &
b01110010 '
b11110111 (
b10001111 )
b11001011 *
b11010111 +
b11100011 ,
b1000 -
b11010111 .
#19
b01000011 #
b00011101 $
b00010010 %
b10010100 &
b11000111 '
b01011001 (
b01111000 )
b01011000 *
b10000111 +
b01101011 ,
b0101 -
b01011001 .
#20
b10001110 #
b00000100 $
b10111110 %
b00101010 &
b01000111 '
b11010100 (
b11001100 )
b11111000 *
b01101110 +
b01101100 ,
b0010 -
b10111110 .
#21
b01100111 #
b10100110 $
b10011000 %
b01011110 &
b00110101 '
b01100100 (
b00110101 )
b00011000 *
b11100100 +
b01111000 ,
b0111 -
b00011000 .
#22
b11110110 #
b00001101 $
b11111101 %
b01001111 &
b10000101 '
b01010101 (
b11010110 )
b11110000 *
b00101000 +
b01100101 ,
b0101 -
b01010101 .
#23
b11100110 #
b10001111 $
b00111100 %
b10111010 &
b01011011 '
b00110101 (
b00101000 )
b11000111 *
b01011011 +
b10001111 ,
b0001 -
b10001111 .
#24
b11110011 #
b11101110 $
b10100010 %
b01010111 &
b00100011 '
b10111011 (
b00111011 )
b10011100 *
b11110000 +
b00110001 ,
b11101110 .
#25
b11101101 #
b10000000 $
b00101110 %
b01000010 &
b01010111 '
b00011110 (
b01101010 )
b10111100 *
b00010011 +
b01010000 ,
b10000000 .
#26
b01010000 #
b00001010 $
b10100110 %
b10000101 &
b00110010 '
b01101101 (
b11100000 )
b11000010 *
b11011010 +
b11010011 ,
b0000 -
b01010000 .
#27
b01111100 #
b00101011 $
b11010011 %
b00110111 &
b01100110 '
b01101111 (
b00101000 )
b10011000 *
b00011000 +
b00010101 ,
b0010 -
b11010011 .
#28
b01000110 #
b01011000 $
b01101111 %
b01100101 &
b11000010 '
b00101011 (
b01111000 )
b00010011 *
b01110110 +
b11001000 ,
b0101 -
b00101011 .
#29
b00011100 #
b01001101 $
b01010000 %
b10001001 &
b00101101 '
b00010010 (
b01100011 )
b00000001 *
b11000010 +
b11100000 ,
b0110 -
b01100011 .
#30
b10010101 #
b00010111 $
b10010010 %
b00000101 &
b00111111 '
b00101010 (
b00011101 )
b01010101 *
b01000011 +
b01100100 ,
b0011 -
b00000101 .
#31
b10110010 #
b11001001 $
b01101111 %
b11011110 &
b01000001 '
b10000010 (
b01010100 )
b00001010 *
b10100000 +
b01110001 ,
b1001 -
b01110001 .
#32
b11110000 #
b11111010 $
b10000101 %
b00000010 &
b01011110 '
b10000110 (
b11000100 )
b00111110 *
b10110010 +
b01011001 ,
b0111 -
b00111110 .
#33
b01000100 #
b01011110 $
b10010101 %
b01101111 &
b01111100 '
b11101010 (
b10110010 )
b11100000 *
b10010111 +
b01100100 ,
b11100000 .
#34
b00000110 #
b01000010 $
b11101010 %
b10001001 &
b10010111 '
b11110100 (
b00101001 )
b00001000 *
b01001100 +
b00011001 ,
b0100 -
b10010111 .
#35
b11010001 #
b00011011 $
b01100000 %
b01010111 &
b11011111 '
b10011110 (
b00001001 )
b00111000 *
b11110100 +
b01001101 ,
b0001 -
b00011011 .
#36
b10001001 #
b10111100 $
b00010011 %
b01110011 &
b01101110 '
b11110011 (
b00001010 )
b11010011 *
b10011100 +
b00010000 ,
b0011 -
b01110011 .
#37
b10000110 #
b10011001 $
b10101100 %
b01111011 &
b11000010 '
b10110100 (
b11000111 )
b11011011 *
b10110111 +
b10011000 ,
b1000 -
b10110111 .
#38
b00010111 #
b11101111 $
b11010101 %
b10110110 &
b11111000 '
b00001110 (
b10101010 )
b01000101 *
b10100101 +
b00110011 ,
b0000 -
b00010111 .
#39
b10111000 #
b10100110 $
b01110000 %
b10101011 &
b10110000 '
b01000011 (
b01000111 )
b11000000 *
b01011001 +
b11001101 ,
b0010 -
b01110000 .
#40
b00000101 #
b01001000 $
b00011100 %
b10111010 &
b00001111 '
b11111000 (
b01110001 )
b10100111 *
b11101110 +
b10001000 ,
b1000 -
b11101110 .
#41
b11000100 #
b00111110 $
b10001110 %
b11010010 &
b11101000 '
b11010100 (
b01110111 )
b00011011 *
b11010110 +
b00101111 ,
b1001 -
b00101111 .
#42
b01000110 #
b11011010 $
b01110001 %
b10001010 &
b00100001 '
b00110010 (
b11100011 )
b11101110 *
b10001100 +
b11101000 ,
b0001 -
b11011010 .
#43
b10101000 #
b10100010 $
b01000110 %
b10100000 &
b00010011 '
b11101110 (
b10001111 )
b10011100 *
b10000100 +
b01010011 ,
b0100 -
b00010011 .
#44
b00010011 #
b00100101 $
b11000011 %
b11100111 &
b10011100 '
b11011110 (
b10111101 )
b11001011 *
b10100000 +
b00000011 ,
b0001 -
b00100101 .
#45
b00010001 #
b10001101 $
b11000110 %
b01000011 &
b01110000 '
b10110100 (
b11001111 )
b01011001 *
b11101011 +
b01111000 ,
b0011 -
b01000011 .
#46
b00110010 #
b00011000 $
b00001111 %
b00100000 &
b10100111 '
b10101011 (
b10100100 )
b11111010 *
b10000101 +
b10110111 ,
b0001 -
b00011000 .
#47
b01001000 #
b10011110 $
b10111011 %
b00100111 &
b01011011 '
b10000110 (
b11000111 )
b01011111 *
b00101011 +
b11011000 ,
b0100 -
b01011011 .
#48
b11110001 #
b00011100 $
b01011101 %
b10100110 &
b11101011 '
b10110110 (
b10010001 )
b01100011 *
b10110001 +
b11000011 ,
b0000 -
b11110001 .
#49
b11000000 #
b11100011 $
b00100011 %
b01101011 &
b10001000 '
b00011110 (
b11110001 )
b00111111 *
b00111101 +
b00111001 ,
b1000 -
b00111101 .
#50
b11111001 #
b01100000 $
b00111001 %
b01111111 &
b00100111 '
b10011000 (
b10101011 )
b00000000 *
b10000101 +
b10011100 ,
b0000 -
b11111001 .
#51
b11100010 #
b01000010 $
b00000111 %
b10011000 &
b11010100 '
b01101011 (
b01001001 )
b10010111 *
b11100111 +
b00001010 ,
b0101 -
b01101011 .
#52
b00001010 #
b01110101 $
b00000011 %
b00101000 &
b01100110 '
b01000010 (
b01100110 )
b10100000 *
b00100000 +
b01011111 ,
b0100 -
b01100110 .
#53
b01011010 #
b11011110 $
b00101000 %
b11110010 &
b10001001 '
b00101000 (
b01110111 )
b00100110 *
b01000100 +
b01011001 ,
b1000 -
b01000100 .
#54
b01001011 #
b11110001 $
b00111100 %
b10110110 &
b00111011 '
b11010100 (
b10011101 )
b01000101 *
b01001111 +
b10101000 ,
b0110 -
b10011101 .
#55
b01010010 #
b11010000 $
b00100001 %
b10010100 &
b00110110 '
b11000001 (
b10110101 )
b10010101 *
b11000001 +
b00001111 ,
b0010 -
b00100001 .
#56
b11101001 #
b00000001 $
b11111101 %
b00010001 &
b01111001 '
b00100011 (
b01010101 )
b11010010 *
b10001100 +
b10100001 ,
b0100 -
b01111001 .
#57
b11001000 #
b01010111 $
b11111111 %
b10011100 &
b11110101 '
b01000100 (
b11101011 )
b10011101 *
b11111110 +
b00111101 ,
b0011 -
b10011100 .
#58
b00011111 #
b11010010 $
b10100100 %
b11100000 &
b10000111 '
b00111001 (
b10100010 )
b10010110 *
b10101101 +
b10001011 ,
b0111 -
b10010110 .
#59
b10101011 #
b10011101 $
b00010000 %
b11001110 &
b11110010 '
b11100011 (
b01011010 )
b10010011 *
b10100111 +
b00100011 ,
b0011 -
b11001110 .
#60
b10100110 #
b10111111 $
b11100000 %
b11101010 &
b10101011 '
b01111101 (
b11101000 )
b11101000 *
b11101010 +
b00001000 ,
b1000 -
b11101010 .
#61
b10001110 #
b11101000 $
b01000001 %
b11001000 &
b10001010 '
b11010111 (
b01110101 )
b00010110 *
b01101111 +
b00100000 ,
b0111 -
b00010110 .
#62
b01111111 #
b11101111 $
b10100101 %
b01100010 &
b01001001 '
b00111001 (
b00001001 )
b01101100 *
b00100100 +
b10101111 ,
b0110 -
b00001001 .
#63
b00000100 #
b10011001 $
b11010111 %
b10000001 &
b10000010 '
b10111111 (
b01101011 )
b10001010 *
b01111010 +
b11111010 ,
b0100 -
b10000010 .
#64
b10111011 #
b11000010 $
b11111101 %
b10010011 &
b00110111 '
b00010011 (
b00000010 )
b01011000 *
b11000110 +
b10000001 ,
b0001 -
b11000010 .
#65
b01101011 #
b11100100 $
b10010000 %
b10100100 &
b11101101 '
b11111101 (
b11001000 )
b10011101 *
b00101001 +
b11001100 ,
b0110 -
b11001000 .
#66
b00000000 #
b01001101 $
b10111000 %
b10111111 &
b10111001 '
b01000010 (
b00111001 )
b10110011 *
b10110101 +
b11110101 ,
b0001 -
b01001101 .
#67
b10110010 #
b10001000 $
b10101100 %
b11000101 &
b10001010 '
b00000100 (
b10001011 )
b00001011 *
b01001011 +
b11110110 ,
b10001000 .
#68
b11011100 #
b10011011 $
b11011101 %
b11011001 &
b01100011 '
b01111010 (
b00000010 )
b00110000 *
b10110000 +
b00000010 ,
b0111 -
b00110000 .
#69
b01101001 #
b11000001 $
b00110110 %
b10101011 &
b11111011 '
b11101001 (
b01100000 )
b11110000 *
b01011110 +
b00010010 ,
b0000 -
b01101001 .
#70
b00001011 #
b11010111 $
b00000010 %
b00001111 &
b01100010 '
b00001101 (
b01011011 )
b01011001 *
b11111101 +
b00110111 ,
b00001011 .
#71
b11011010 #
b00010000 $
b01010111 %
b01010100 &
b00010010 '
b10000111 (
b00000100 )
b00010100 *
b00000101 +
b01101101 ,
b1001 -
b01101101 .
#72
b00111011 #
b00011001 $
b11010000 %
b00100101 &
b01111001 '
b11000000 (
b10000011 )
b10001100 *
b00111000 +
b10001110 ,
b0011 -
b00100101 .
#73
b00111010 #
b10011110 $
b11000110 %
b01001000 &
b11111001 '
b00011111 (
b01000101 )
b00110000 *
b00010011 +
b00011111 ,
b1000 -
b00010011 .
#74
b01101010 #
b01110011 $
b01010010 %
b11110010 &
b01110111 '
b01100110 (
b11110111 )
b11100101 *
b00111011 +
b00110010 ,
b0010 -
b01010010 .
#75
b00001100 #
b01010111 $
b01110111 %
b11001100 &
b11011011 '
b00000011 (
b00000101 )
b01101001 *
b01100111 +
b00111111 ,
b0001 -
b01010111 .
#76
b00101101 #
b10000111 $
b00000000 %
b01001100 &
b11001100 '
b00110000 (
b01011111 )
b11101011 *
b01110000 +
b11001001 ,
b0000 -
b00101101 .
#77
b11000010 #
b10111011 $
b11010110 %
b00101000 &
b10110010 '
b10111011 (
b01100100 )
b11100101 *
b10111001 +
b01110000 ,
b11000010 .
#78
b00110000 #
b00111100 $
b00010111 %
b00110100 &
b01000001 '
b10000001 (
b10011011 )
b10000001 *
b10001000 +
b11001000 ,
b0110 -
b10011011 .
#79
b10001001 #
b00010100 $
b11010101 %
b10111001 &
b01110011 '
b11000000 (
b00101010 )
b00111100 *
b00011111 +
b11101100 ,
b0100 -
b01110011 .
#80
b11110101 #
b00010101 $
b10101010 %
b10110000 &
b01111001 '
b10001111 (
b01101001 )
b11101001 *
b11001100 +
b10011001 ,
b0001 -
b00010101 .
#81
b11100011 #
b11001101 $
b01100111 %
b01100100 &
b01101000 '
b11101000 (
b11101101 )
b00110000 *
b11110000 +
b01110110 ,
b1000 -
b11110000 .
#82
b11000101 #
b00101111 $
b10110111 %
b10000110 &
b01011001 '
b11110100 (
b10100101 )
b01000110 *
b11101100 +
b10011010 ,
b0111 -
b01000110 .
#83
b10010110 #
b01001010 $
b11010100 %
b00100110 &
b10110011 '
b10111101 (
b11110010 )
b01001100 *
b11100010 +
b11010101 ,
b0110 -
b11110010 .
#84
b01001001 #
b00111010 $
b10000010 %
b00110001 &
b00100111 '
b10110011 (
b00100010 )
b10011101 *
b11110111 +
b11100111 ,
b1000 -
b11110111 .
#85
b10101111 #
b01101101 $
b00100110 %
b10100011 &
b00010010 '
b01101100 (
b10001111 )
b10101100 *
b11000111 +
b00100101 ,
b0110 -
b10001111 .
#86
b10011011 #
b01001011 $
b10101001 %
b01011000 &
b00111101 '
b11110110 (
b00111010 )
b00010011 *
b00010000 +
b10000100 ,
b1001 -
b10000100 .
#87
b10010010 #
b10110101 $
b01110100 %
b01000101 &
b11010111 '
b00010001 (
b00111101 )
b10111111 *
b11011101 +
b11101100 ,
b0010 -
b01110100 .
#88
b00000011 #
b10001111 $
b00111111 %
b01101111 &
b00011110 '
b11101011 (
b00110110 )
b01000011 *
b11100010 +
b11010001 ,
b0011 -
b01101111 .
#89
b10001011 #
b00101001 $
b11001100 %
b10000001 &
b01100100 '
b11011111 (
b10010001 )
b11101000 *
b00101100 +
b00100100 ,
b1001 -
b00100100 .
#90
b10100000 #
b01101001 $
b01110101 %
b10110001 &
b10100110 '
b00110100 (
b10001111 )
b10010010 *
b01100000 +
b10010010 ,
b0001 -
b01101001 .
#91
b10011111 #
b00000010 $
b00111111 %
b10001011 &
b00111000 '
b10000011 (
b01101101 )
b00001010 *
b00010010 +
b11111000 ,
b0011 -
b10001011 .
#92
b11011110 #
b01111010 $
b10010111 %
b10111110 &
b00001011 '
b01111111 (
b11101010 )
b00101111 *
b00011101 +
b10001011 ,
b0111 -
b00101111 .
#93
b10010010 #
b00111100 $
b00111111 %
b11000110 &
b11001011 '
b11010010 (
b00100110 )
b01011110 *
b11110011 +
b11000110 ,
b1000 -
b11110011 .
#94
b00110011 #
b01010001 $
b10011000 %
b10110110 &
b10111110 '
b10100010 (
b11001000 )
b10110110 *
b11010110 +
b10100110 ,
b0110 -
b11001000 .
#95
b01101101 #
b01100100 $
b00111100 %
b11101101 &
b01001111 '
b01101011 (
b00001010 )
b11011010 *
b00000100 +
b10011100 ,
b0010 -
b00111100 .
#96
b01000100 #
b01100010 $
b11100010 %
b00010110 &
b10001000 '
b01000000 (
b00001001 )
b01001110 *
b10100000 +
b00111100 ,
b0011 -
b00010110 .
#97
b00111000 #
b11110010 $
b01011101 %
b11011011 &
b10111010 '
b00010100 (
b10110001 )
b01100001 *
b01000100 +
b00011110 ,
b0001 -
b11110010 .
#98
b10000000 #
b00001011 $
b00010100 %
b11101100 &
b00010101 '
b11101110 (
b11110000 )
b10110001 *
b00000101 +
b00110100 ,
b00001011 .
#99
b11100111 #
b01001010 $
b10011100 %
b00100111 &
b01010100 '
b11101010 (
b11000111 )
b10010000 *
b10001010 +
b11111111 ,
b01001010 .
#100
b11011010 $
b00111101 %
b11111011 &
b10001011 '
b10011110 (
b01000000 )
b10101010 *
b01100100 +
b11000000 ,
b0101 -
b10011110 .
#101
b01111000 #
b10101100 $
b11001011 %
b01100111 &
b10011101 '
b01111100 (
b01101100 )
b11010001 *
b10010000 +
b01010011 ,
b0000 -
b01111000 .
#102
b00101100 #
b01111010 $
b01110000 %
b00010110 &
b01000001 '
b00000000 (
b10100000 )
b01000000 *
b10000011 +
b10001000 ,
b0001 -
b01111010 .
#103
b11000001 #
b10000011 $
b10100110 %
b01011111 &
b11000011 '
b01010000 (
b11000011 )
b10000100 *
b00000110 +
b00111100 ,
b0000 -
b11000001 .
#104
b11010001 #
b10100011 $
b11001101 %
b01001101 &
b00001111 '
b10011111 (
b11011101 )
b01100010 *
b10111011 +
b00001001 ,
b0010 -
b11001101 .
#105
b00101011 #
b00100000 $
b00011101 %
b00101011 &
b11000000 '
b01011101 (
b10101111 )
b01001000 *
b01111000 +
b01110000 ,
b0000 -
b00101011 .
#106
b00011111 #
b11001111 $
b10001111 %
b01101111 &
b10010011 '
b00010011 (
b01110101 )
b11001111 *
b01000100 +
b01000110 ,
b0110 -
b01110101 .
#107
b00010001 #
b10010100 $
b10000001 %
b10110000 &
b01110001 '
b11100011 (
b01101011 )
b01111011 *
b10111111 +
b10010110 ,
b0111 -
b01111011 .
#108
b11011100 #
b11000010 $
b01011011 %
b00111001 &
b10100100 (
b10110010 )
b11100001 *
b01110000 +
b11010001 ,
b0010 -
b01011011 .
#109
b11111111 #
b01000000 $
b01000011 %
b00010011 &
b10110110 '
b00010010 (
b01010111 )
b11111100 *
b10000100 +
b01101000 ,
b1000 -
b10000100 .
#110
b00000101 #
b00011001 $
b00000010 %
b11101000 &
b10000100 '
b01111101 (
b10100111 )
b00011011 *
b00011000 +
b10000011 ,
b0101 -
b01111101 .
#111
b01110011 #
b10111101 $
b01001110 %
b00010111 &
b01101111 '
b00101111 (
b10000111 )
b01000000 *
b11011111 +
b10000111 ,
b0000 -
b01110011 .
#112
b00100011 #
b10011010 $
b00110110 %
b00110101 &
b11110001 '
b00110011 (
b10111010 )
b01011001 *
b11000011 +
b10111111 ,
b0100 -
b11110001 .
#113
b11000101 #
b10101000 $
b11110111 %
b01000010 &
b01001111 '
b00010010 (
b01011010 )
b11010011 *
b11101111 +
b11001110 ,
b1000 -
b11101111 .
#114
b00111101 #
b11100101 $
b11111111 %
b01101100 &
b01101101 '
b00111111 (
b01001011 )
b11110100 *
b10111111 +
b01101110 ,
b0000 -
b00111101 .
#115
b11110110 #
b10100100 $
b01111111 %
b00101001 &
b01011110 '
b11011000 (
b11101100 )
b00011101 *
b01001011 +
b10110010 ,
b0001 -
b10100100 .
#116
b01000010 #
b11110100 $
b00010101 %
b01010100 &
b01001111 '
b11101000 (
b01000011 )
b01111000 +
b10000000 ,
b0100 -
b01001111 .
#117
b01110111 #
b11101100 $
b01101111 %
b10110110 &
b00110111 '
b01100011 (
b01110101 )
b10100110 *
b11110001 +
b01101011 ,
b00110111 .
#118
b01110000 #
b10010100 $
b10101000 %
b01001001 &
b10000001 '
b11000101 (
b10010100 )
b00110011 *
b10001011 +
b11010110 ,
b0001 -
b10010100 .
#119
b10100000 #
b00101010 $
b01110110 %
b10001000 &
b01101101 '
b10010011 (
b00000000 )
b11101101 *
b10010110 +
b01110111 ,
b0011 -
b10001000 .
#120
b00000101 #
b00101101 $
b00010000 %
b01101001 &
b10100010 '
b10110110 (
b01011010 )
b00001110 *
b00000000 +
b11001011 ,
b0110 -
b01011010 .
#121
b10101000 #
b00010100 $
b00100011 %
b01101110 &
b10101000 '
b01010110 (
b11111001 )
b01111110 *
b01111110 +
b10011001 ,
b11111001 .
#122
b11110100 #
b00100001 $
b00010101 %
b10001000 &
b00100001 '
b00000010 (
b00011110 )
b10011000 *
b11011011 +
b00100011 ,
b1001 -
b00100011 .
#123
b11101011 #
b10001100 $
b01100111 %
b10100010 &
b11100111 '
b01110101 (
b10100010 )
b10110010 *
b00011000 +
b01001011 ,
b0110 -
b10100010 .
#124
b00111011 #
b10111001 $
b01101110 %
b10010010 &
b10110010 '
b11101100 (
b00010000 )
b01001011 *
b10010100 +
b00000100 ,
b00010000 .
#125
b10101001 #
b10001100 $
b10001101 %
b10101011 &
b10101010 '
b00100101 (
b10000110 )
b11001110 *
b11101010 +
b01110001 ,
b0010 -
b10001101 .
#126
b01010001 #
b00010011 $
b01000001 %
b11000111 &
b10110110 '
b11110011 (
b11011111 )
b00000001 *
b10111001 +
b00011010 ,
b0110 -
b11011111 .
#127
b00100111 #
b10101100 $
b01101100 %
b00010011 &
b10111100 '
b10110111 (
b10100111 )
b11000001 *
b00100011 +
b01010000 ,
b0111 -
b11000001 .
#128
b10110000 #
b11111011 $
b11111000 %
b11010101 &
b10000001 '
b11000110 (
b10111111 )
b11110011 *
b00100000 +
b00010000 ,
b0110 -
b10111111 .
#129
b01100010 #
b11010111 $
b10111100 %
b01010101 &
b10110110 '
b10111101 (
b00001111 )
b11010001 *
b01110111 +
b00110110 ,
b0111 -
b11010001 .
#130
b11100011 #
b01001010 $
b00111010 %
b10011010 &
b11110001 '
b11111011 (
b10111101 )
b01000010 *
b01001000 +
b01101101 ,
b01000010 .
#131
b01000000 #
b01000010 $
b10111111 %
b00000110 &
b00000001 '
b10110010 (
b00100111 )
b00010010 *
b10111000 +
b10001001 ,
b0011 -
b00000110 .
#132
b01110101 #
b11011110 $
b10100000 %
b00110010 &
b11101101 '
b01110001 (
b10101010 )
b00100100 *
b11101110 +
b10001101 ,
b0010 -
b10100000 .
#133
b00101000 #
b00101000 $
b01011111 %
b00100011 &
b11100101 '
b10100001 (
b01101100 )
b01010011 *
b11011111 +
b10101100 ,
b0001 -
b00101000 .
#134
b10011110 #
b10110011 $
b10010111 %
b01010000 &
b11011010 '
b10101001 (
b00001000 )
b01100011 *
b10010010 +
b01111101 ,
b1001 -
b01111101 .
#135
b00110010 #
b10110000 $
b00101111 %
b10100011 &
b01011010 '
b01010011 (
b10010010 )
b11100111 *
b11000001 +
b10111010 ,
b0001 -
b10110000 .
#136
b00100000 #
b11011110 $
b11110101 %
b11000010 &
b01001010 '
b01001000 (
b10100001 )
b11110110 *
b11011101 +
b00111111 ,
b1001 -
b00111111 .
#137
b01110100 #
b10001111 $
b10000011 %
b00011101 &
b10010111 '
b11100110 (
b10110000 )
b00010101 *
b00101000 +
b11100010 ,
b0111 -
b00010101 .
#138
b01010111 #
b10000110 $
b00011111 %
b10101010 &
b00011000 '
b00000110 (
b01101011 )
b11010010 *
b00010110 +
b10001011 ,
b0110 -
b01101011 .
#139
b00001011 #
b01001101 $
b11111010 %
b01010011 &
b11101110 '
b11110001 (
b00110000 )
b00101101 *
b10011010 +
b10100101 ,
b0000 -
b00001011 .
#140
b00011110 #
b11000010 $
b01010100 %
b00000100 &
b01110010 '
b01101001 (
b00101100 )
b01010101 *
b00101110 +
b10000011 ,
b0111 -
b01010101 .
#141
b01001101 #
b00101101 $
b11110011 %
b01010011 &
b10011000 '
b11000101 (
b01101001 )
b00100100 *
b01110110 +
b01110100 ,
b0001 -
b00101101 .
#142
b01110000 #
b11000111 $
b01100000 %
b01100001 &
b11111000 '
b10001101 (
b11111100 )
b10011101 *
b01001010 +
b00011010 ,
b0111 -
b10011101 .
#143
b10011110 #
b00011110 $
b11010010 %
b00000111 &
b01001011 '
b00100111 (
b00110101 )
b11001110 *
b00000010 +
b10000010 ,
b0010 -
b11010010 .
#144
b11110101 #
b11010101 $
b10010100 %
b10111010 &
b00111111 '
b10111000 (
b00110000 )
b10110011 *
b00101010 +
b10100001 ,
b0111 -
b10110011 .
#145
b10001010 #
b00000010 $
b01110011 %
b00010111 &
b11111110 '
b00010000 (
b01100001 )
b00011000 *
b01101111 +
b11111111 ,
b0011 -
b00010111 .
#146
b01000001 #
b00000110 $
b10000010 %
b01101000 &
b00111011 '
b01010000 (
b01101010 )
b10111101 *
b01001100 +
b01011111 ,
b0101 -
b01010000 .
#147
b11100001 #
b00011010 $
b11010010 %
b10011001 &
b01001010 '
b10000101 (
b11000011 )
b11101011 *
b00000000 +
b01001101 ,
b0000 -
b11100001 .
#148
b01110011 #
b01100101 $
b11101100 %
b10000011 &
b11000110 '
b00000101 (
b11110011 )
b11000110 *
b00111100 +
b00110100 ,
b0100 -
b11000110 .
#149
b10111110 #
b10011101 $
b00001000 %
b00001110 &
b00000111 '
b11000101 (
b01011011 )
b01100111 *
b01011000 +
b00111100 ,
b0101 -
b11000101 .
